[
    {
        "key": "A7dB-ykxc-kQWh",
        "edge": "PLUS_EV_AVERAGE",
        "lastFoundAt": "2024-10-23T02:38:01.015Z",
        "type": "MONEYLINE",
        "market_name": "Atlanta Hawks @ Boston Celtics",
        "participants": [
            "Atlanta Hawks",
            "Boston Celtics"
        ],
        "outcome_payout": 6.3,
        "source": "FAN_DUEL",
        "participant": "Atlanta Hawks",
        "sport": "BASKETBALL",
        "implied_probability": 16.444181,
        "profit_potential": 530.0,
        "EV": 3.5983403,
        "event_start_time": "2024-11-12T23:00:00.000Z",
        "competition_instance_name": "2024-25 National Basketball Association"
    },
    {
        "key": "Jqov-ykxc-b75Z",
        "edge": "PLUS_EV_AVERAGE",
        "lastFoundAt": "2024-10-23T02:38:01.015Z",
        "type": "MONEYLINE",
        "market_name": "Indiana Pacers @ Detroit Pistons",
        "participants": [
            "Detroit Pistons",
            "Indiana Pacers"
        ],
        "outcome_payout": 2.76,
        "source": "FAN_DUEL",
        "participant": "Detroit Pistons",
        "sport": "BASKETBALL",
        "implied_probability": 36.232594,
        "profit_potential": 176.0,
        "EV": 0.00195944,
        "event_start_time": "2024-10-23T23:00:00.000Z",
        "competition_instance_name": "2024-25 National Basketball Association"
    },
    {
        "key": "x7FW-ykxc-KVyz",
        "edge": "PLUS_EV_AVERAGE",
        "lastFoundAt": "2024-10-23T02:38:01.015Z",
        "type": "MONEYLINE",
        "market_name": "Boston Celtics @ Washington Wizards",
        "participants": [
            "Boston Celtics",
            "Washington Wizards"
        ],
        "outcome_payout": 7.25,
        "source": "DRAFT_KINGS",
        "participant": "Washington Wizards",
        "sport": "BASKETBALL",
        "implied_probability": 13.84034,
        "profit_potential": 625.0,
        "EV": 0.342465,
        "event_start_time": "2024-10-24T23:00:00.000Z",
        "competition_instance_name": "2024-25 National Basketball Association"
    },
    {
        "key": "us0A-ykxc-2dAX",
        "edge": "PLUS_EV_AVERAGE",
        "lastFoundAt": "2024-10-23T02:38:01.015Z",
        "type": "MONEYLINE_3WAY",
        "market_name": "Sheffield Wednesday @ Portsmouth",
        "participants": [
            "Portsmouth",
            "Sheffield Wednesday"
        ],
        "outcome_payout": 3.25,
        "source": "DRAFT_KINGS",
        "participant": "Portsmouth",
        "sport": "SOCCER",
        "implied_probability": 31.313926,
        "profit_potential": 225.0,
        "EV": 1.7702595,
        "event_start_time": "2024-10-25T19:00:00.000Z",
        "competition_instance_name": "2024-25 English Football League Championship"
    },
    {
        "key": "Xci0-ykxc-6UKZ",
        "edge": "PLUS_EV_AVERAGE",
        "lastFoundAt": "2024-10-23T02:38:01.015Z",
        "type": "MONEYLINE_3WAY",
        "market_name": "New York City FC @ FC Cincinnati",
        "participants": [
            "New York City FC",
            "FC Cincinnati"
        ],
        "outcome_payout": 4.2,
        "source": "BET_RIVERS",
        "participant": null,
        "sport": null,
        "implied_probability": 24.044825,
        "profit_potential": 320.0,
        "EV": 0.988265,
        "event_start_time": "2024-10-28T22:45:00.000Z",
        "competition_instance_name": "2024 Major League Soccer"
    },
    {
        "key": "ZrpD-ykxc-aNet",
        "edge": "PLUS_EV_AVERAGE",
        "lastFoundAt": "2024-10-23T02:38:01.015Z",
        "type": "MONEYLINE_3WAY",
        "market_name": "Athletic Bilbao @ RCD Mallorca",
        "participants": [
            "Athletic Bilbao",
            "RCD Mallorca"
        ],
        "outcome_payout": 3.2,
        "source": "BET_RIVERS",
        "participant": "RCD Mallorca",
        "sport": "SOCCER",
        "implied_probability": 31.275308,
        "profit_potential": 220.0,
        "EV": 0.0809856,
        "event_start_time": "2024-10-28T20:00:00.000Z",
        "competition_instance_name": "2024-25 Spanish La Liga"
    },
    {
        "key": "3CgH-ykxc-UmYt",
        "edge": "PLUS_EV_AVERAGE",
        "lastFoundAt": "2024-10-23T02:38:01.015Z",
        "type": "MONEYLINE_3WAY",
        "market_name": "Osasuna @ Real Sociedad",
        "participants": [
            "Real Sociedad",
            "Osasuna"
        ],
        "outcome_payout": 4.8,
        "source": "FAN_DUEL",
        "participant": "Osasuna",
        "sport": "SOCCER",
        "implied_probability": 21.286694,
        "profit_potential": 380.0,
        "EV": 2.1761312,
        "event_start_time": "2024-10-27T20:00:00.000Z",
        "competition_instance_name": "2024-25 Spanish La Liga"
    },
    {
        "key": "HnLm-ykxc-Q56o",
        "edge": "PLUS_EV_AVERAGE",
        "lastFoundAt": "2024-10-23T02:38:01.015Z",
        "type": "MONEYLINE_3WAY",
        "market_name": "Espanyol @ Barcelona",
        "participants": [
            "Barcelona",
            "Espanyol"
        ],
        "outcome_payout": 17.0,
        "source": "BET_RIVERS",
        "participant": "Espanyol",
        "sport": "SOCCER",
        "implied_probability": 6.916902,
        "profit_potential": 1600.0,
        "EV": 17.587334,
        "event_start_time": "2024-11-03T15:15:00.000Z",
        "competition_instance_name": "2024-25 Spanish La Liga"
    },
    {
        "key": "IccY-ykxc-Q0JA",
        "edge": "PLUS_EV_AVERAGE",
        "lastFoundAt": "2024-10-23T02:38:01.015Z",
        "type": "MONEYLINE_3WAY",
        "market_name": "Espanyol @ Barcelona",
        "participants": [
            "Barcelona",
            "Espanyol"
        ],
        "outcome_payout": 17.0,
        "source": "BET_PARX",
        "participant": "Espanyol",
        "sport": "SOCCER",
        "implied_probability": 6.916902,
        "profit_potential": 1600.0,
        "EV": 17.587334,
        "event_start_time": "2024-11-03T15:15:00.000Z",
        "competition_instance_name": "2024-25 Spanish La Liga"
    },
    {
        "key": "oe1t-ykxc-4Kdo",
        "edge": "PLUS_EV_AVERAGE",
        "lastFoundAt": "2024-10-23T02:38:01.015Z",
        "type": "MONEYLINE_3WAY",
        "market_name": "Osasuna @ Real Sociedad",
        "participants": [
            "Real Sociedad",
            "Osasuna"
        ],
        "outcome_payout": 4.7,
        "source": "BOVADA",
        "participant": "Osasuna",
        "sport": "SOCCER",
        "implied_probability": 21.286694,
        "profit_potential": 370.0,
        "EV": 0.0474618,
        "event_start_time": "2024-10-27T20:00:00.000Z",
        "competition_instance_name": "2024-25 Spanish La Liga"
    },
    {
        "key": "RjiL-ykxc-7J9B",
        "edge": "PLUS_EV_AVERAGE",
        "lastFoundAt": "2024-10-23T02:38:01.015Z",
        "type": "MONEYLINE_3WAY",
        "market_name": "Osasuna @ Real Sociedad",
        "participants": [
            "Real Sociedad",
            "Osasuna"
        ],
        "outcome_payout": 4.1,
        "source": "BET_RIVERS",
        "participant": null,
        "sport": null,
        "implied_probability": 24.704382,
        "profit_potential": 310.0,
        "EV": 1.2879662,
        "event_start_time": "2024-10-27T20:00:00.000Z",
        "competition_instance_name": "2024-25 Spanish La Liga"
    },
    {
        "key": "5Dgg-ykxc-o60n",
        "edge": "PLUS_EV_AVERAGE",
        "lastFoundAt": "2024-10-23T02:38:01.015Z",
        "type": "MONEYLINE",
        "market_name": "Louisville @ Boston College",
        "participants": [
            "Boston College",
            "Louisville"
        ],
        "outcome_payout": 3.4,
        "source": "ESPN_BET",
        "participant": "Boston College",
        "sport": "AMERICAN_FOOTBALL",
        "implied_probability": 29.689271,
        "profit_potential": 240.0,
        "EV": 0.9435214,
        "event_start_time": "2024-10-25T23:30:00.000Z",
        "competition_instance_name": "2024 NCAA Division I Football"
    },
    {
        "key": "guQW-ykxc-HODC",
        "edge": "PLUS_EV_AVERAGE",
        "lastFoundAt": "2024-10-23T02:38:01.015Z",
        "type": "MONEYLINE",
        "market_name": "Louisville @ Boston College",
        "participants": [
            "Boston College",
            "Louisville"
        ],
        "outcome_payout": 3.4,
        "source": "BOVADA",
        "participant": "Boston College",
        "sport": "AMERICAN_FOOTBALL",
        "implied_probability": 29.689271,
        "profit_potential": 240.0,
        "EV": 0.9435214,
        "event_start_time": "2024-10-25T23:30:00.000Z",
        "competition_instance_name": "2024 NCAA Division I Football"
    },
    {
        "key": "hOzI-ykxc-hSIM",
        "edge": "PLUS_EV_AVERAGE",
        "lastFoundAt": "2024-10-23T02:38:01.015Z",
        "type": "MONEYLINE",
        "market_name": "Georgia State @ Appalachian State",
        "participants": [
            "Appalachian State",
            "Georgia State"
        ],
        "outcome_payout": 3.55,
        "source": "BOVADA",
        "participant": "Georgia State",
        "sport": "AMERICAN_FOOTBALL",
        "implied_probability": 28.326647,
        "profit_potential": 255.0,
        "EV": 0.55959685,
        "event_start_time": "2024-10-26T16:00:00.000Z",
        "competition_instance_name": "2024 NCAA Division I Football"
    },
    {
        "key": "KVjn-ykxc-Ew2Q",
        "edge": "PLUS_EV_AVERAGE",
        "lastFoundAt": "2024-10-23T02:38:01.015Z",
        "type": "MONEYLINE",
        "market_name": "Arkansas @ Mississippi State",
        "participants": [
            "Mississippi State",
            "Arkansas"
        ],
        "outcome_payout": 3.05,
        "source": "BOVADA",
        "participant": "Mississippi State",
        "sport": "AMERICAN_FOOTBALL",
        "implied_probability": 32.925494,
        "profit_potential": 205.0,
        "EV": 0.4227567,
        "event_start_time": "2024-10-26T16:45:00.000Z",
        "competition_instance_name": "2024 NCAA Division I Football"
    },
    {
        "key": "lgmn-ykxc-5hjC",
        "edge": "PLUS_EV_AVERAGE",
        "lastFoundAt": "2024-10-23T02:38:01.015Z",
        "type": "MONEYLINE",
        "market_name": "Tulane @ North Texas",
        "participants": [
            "Tulane",
            "North Texas"
        ],
        "outcome_payout": 3.6,
        "source": "BOVADA",
        "participant": "North Texas",
        "sport": "AMERICAN_FOOTBALL",
        "implied_probability": 28.782471,
        "profit_potential": 260.0,
        "EV": 3.6168956,
        "event_start_time": "2024-10-26T16:00:00.000Z",
        "competition_instance_name": "2024 NCAA Division I Football"
    },
    {
        "key": "5tYw-ykxc-Nwjf",
        "edge": "PLUS_EV_AVERAGE",
        "lastFoundAt": "2024-10-23T02:38:01.015Z",
        "type": "MONEYLINE",
        "market_name": "Oklahoma @ Ole Miss",
        "participants": [
            "Oklahoma",
            "Ole Miss"
        ],
        "outcome_payout": 9.9,
        "source": "FAN_DUEL",
        "participant": "Oklahoma",
        "sport": "AMERICAN_FOOTBALL",
        "implied_probability": 10.486728,
        "profit_potential": 890.0,
        "EV": 3.8186072,
        "event_start_time": "2024-10-26T17:00:00.000Z",
        "competition_instance_name": "2024 NCAA Division I Football"
    },
    {
        "key": "q8vC-ykxc-Bznt",
        "edge": "PLUS_EV_AVERAGE",
        "lastFoundAt": "2024-10-23T02:38:01.015Z",
        "type": "MONEYLINE",
        "market_name": "Middle Tennessee @ Jacksonville State",
        "participants": [
            "Middle Tennessee",
            "Jacksonville State"
        ],
        "outcome_payout": 9.9,
        "source": "FAN_DUEL",
        "participant": "Middle Tennessee",
        "sport": "AMERICAN_FOOTBALL",
        "implied_probability": 10.327831,
        "profit_potential": 890.0,
        "EV": 2.2455269,
        "event_start_time": "2024-10-23T23:30:00.000Z",
        "competition_instance_name": "2024 NCAA Division I Football"
    },
    {
        "key": "2DTl-ykxc-n9ba",
        "edge": "PLUS_EV_AVERAGE",
        "lastFoundAt": "2024-10-23T02:38:01.015Z",
        "type": "MONEYLINE",
        "market_name": "Charlotte @ Memphis",
        "participants": [
            "Memphis",
            "Charlotte"
        ],
        "outcome_payout": 8.0,
        "source": "ESPN_BET",
        "participant": "Charlotte",
        "sport": "AMERICAN_FOOTBALL",
        "implied_probability": 12.588799,
        "profit_potential": 700.0,
        "EV": 0.710392,
        "event_start_time": "2024-10-26T16:00:00.000Z",
        "competition_instance_name": "2024 NCAA Division I Football"
    },
    {
        "key": "e811-ykxc-sdqS",
        "edge": "PLUS_EV_AVERAGE",
        "lastFoundAt": "2024-10-23T02:38:01.015Z",
        "type": "MONEYLINE",
        "market_name": "Charlotte @ Memphis",
        "participants": [
            "Memphis",
            "Charlotte"
        ],
        "outcome_payout": 8.0,
        "source": "BET_PARX",
        "participant": "Charlotte",
        "sport": "AMERICAN_FOOTBALL",
        "implied_probability": 12.588799,
        "profit_potential": 700.0,
        "EV": 0.710392,
        "event_start_time": "2024-10-26T16:00:00.000Z",
        "competition_instance_name": "2024 NCAA Division I Football"
    },
    {
        "key": "hiRE-ykxc-CCZF",
        "edge": "PLUS_EV_AVERAGE",
        "lastFoundAt": "2024-10-23T02:38:01.015Z",
        "type": "MONEYLINE",
        "market_name": "Nebraska @ Ohio State",
        "participants": [
            "Ohio State",
            "Nebraska"
        ],
        "outcome_payout": 17.0,
        "source": "FAN_DUEL",
        "participant": "Nebraska",
        "sport": "AMERICAN_FOOTBALL",
        "implied_probability": 5.990132,
        "profit_potential": 1600.0,
        "EV": 1.832244,
        "event_start_time": "2024-10-26T17:00:00.000Z",
        "competition_instance_name": "2024 NCAA Division I Football"
    },
    {
        "key": "qmeX-ykxc-WcTp",
        "edge": "PLUS_EV_AVERAGE",
        "lastFoundAt": "2024-10-23T02:38:01.015Z",
        "type": "MONEYLINE",
        "market_name": "Nebraska @ Ohio State",
        "participants": [
            "Ohio State",
            "Nebraska"
        ],
        "outcome_payout": 19.0,
        "source": "ESPN_BET",
        "participant": "Nebraska",
        "sport": "AMERICAN_FOOTBALL",
        "implied_probability": 5.990132,
        "profit_potential": 1800.0,
        "EV": 13.812508,
        "event_start_time": "2024-10-26T17:00:00.000Z",
        "competition_instance_name": "2024 NCAA Division I Football"
    },
    {
        "key": "vugJ-ykxc-tdv8",
        "edge": "PLUS_EV_AVERAGE",
        "lastFoundAt": "2024-10-23T02:38:01.015Z",
        "type": "MONEYLINE_3WAY",
        "market_name": "Liverpool @ Arsenal FC",
        "participants": [
            "Liverpool",
            "Arsenal FC"
        ],
        "outcome_payout": 3.25,
        "source": "BET_RIVERS",
        "participant": "Liverpool",
        "sport": "SOCCER",
        "implied_probability": 30.8319,
        "profit_potential": 225.0,
        "EV": 0.203675,
        "event_start_time": "2024-10-27T16:30:00.000Z",
        "competition_instance_name": "2024-25 English Premier League"
    },
    {
        "key": "qu9B-ykxc-Zwv6",
        "edge": "PLUS_EV_AVERAGE",
        "lastFoundAt": "2024-10-23T02:38:01.015Z",
        "type": "MONEYLINE_3WAY",
        "market_name": "Brighton & Hove Albion @ Liverpool",
        "participants": [
            "Brighton & Hove Albion",
            "Liverpool"
        ],
        "outcome_payout": 7.0,
        "source": "FAN_DUEL",
        "participant": "Brighton & Hove Albion",
        "sport": "SOCCER",
        "implied_probability": 14.520162,
        "profit_potential": 600.0,
        "EV": 1.641134,
        "event_start_time": "2024-11-02T15:00:00.000Z",
        "competition_instance_name": "2024-25 English Premier League"
    },
    {
        "key": "p6Dh-ykxc-oSE2",
        "edge": "PLUS_EV_AVERAGE",
        "lastFoundAt": "2024-10-23T02:38:01.015Z",
        "type": "MONEYLINE_3WAY",
        "market_name": "Brighton & Hove Albion @ Liverpool",
        "participants": [
            "Brighton & Hove Albion",
            "Liverpool"
        ],
        "outcome_payout": 7.0,
        "source": "BET_PARX",
        "participant": "Brighton & Hove Albion",
        "sport": "SOCCER",
        "implied_probability": 14.520162,
        "profit_potential": 600.0,
        "EV": 1.641134,
        "event_start_time": "2024-11-02T15:00:00.000Z",
        "competition_instance_name": "2024-25 English Premier League"
    },
    {
        "key": "yODW-ykxc-NQ1P",
        "edge": "PLUS_EV_AVERAGE",
        "lastFoundAt": "2024-10-23T02:38:01.015Z",
        "type": "MONEYLINE_3WAY",
        "market_name": "Brighton & Hove Albion @ Liverpool",
        "participants": [
            "Brighton & Hove Albion",
            "Liverpool"
        ],
        "outcome_payout": 7.0,
        "source": "BET_RIVERS",
        "participant": "Brighton & Hove Albion",
        "sport": "SOCCER",
        "implied_probability": 14.520162,
        "profit_potential": 600.0,
        "EV": 1.641134,
        "event_start_time": "2024-11-02T15:00:00.000Z",
        "competition_instance_name": "2024-25 English Premier League"
    },
    {
        "key": "xP6l-ykxc-sdfq",
        "edge": "PLUS_EV_AVERAGE",
        "lastFoundAt": "2024-10-23T02:38:01.015Z",
        "type": "MONEYLINE_3WAY",
        "market_name": "Brighton & Hove Albion @ Liverpool",
        "participants": [
            "Brighton & Hove Albion",
            "Liverpool"
        ],
        "outcome_payout": 5.5,
        "source": "DRAFT_KINGS",
        "participant": null,
        "sport": null,
        "implied_probability": 18.800293,
        "profit_potential": 450.0,
        "EV": 3.4016115,
        "event_start_time": "2024-11-02T15:00:00.000Z",
        "competition_instance_name": "2024-25 English Premier League"
    },
    {
        "key": "cgDW-ykxc-QLQE",
        "edge": "PLUS_EV_AVERAGE",
        "lastFoundAt": "2024-10-23T02:38:01.015Z",
        "type": "MONEYLINE_3WAY",
        "market_name": "Manchester City @ AFC Bournemouth",
        "participants": [
            "Manchester City",
            "AFC Bournemouth"
        ],
        "outcome_payout": 6.1,
        "source": "BET_PARX",
        "participant": "AFC Bournemouth",
        "sport": "SOCCER",
        "implied_probability": 16.539568,
        "profit_potential": 510.0,
        "EV": 0.8913648,
        "event_start_time": "2024-11-02T15:00:00.000Z",
        "competition_instance_name": "2024-25 English Premier League"
    },
    {
        "key": "jvsK-ykxc-TvFU",
        "edge": "PLUS_EV_AVERAGE",
        "lastFoundAt": "2024-10-23T02:38:01.015Z",
        "type": "MONEYLINE_3WAY",
        "market_name": "Manchester City @ AFC Bournemouth",
        "participants": [
            "Manchester City",
            "AFC Bournemouth"
        ],
        "outcome_payout": 6.25,
        "source": "BET_RIVERS",
        "participant": "AFC Bournemouth",
        "sport": "SOCCER",
        "implied_probability": 16.539568,
        "profit_potential": 525.0,
        "EV": 3.3723,
        "event_start_time": "2024-11-02T15:00:00.000Z",
        "competition_instance_name": "2024-25 English Premier League"
    },
    {
        "key": "gszr-ykxc-91n0",
        "edge": "PLUS_EV_AVERAGE",
        "lastFoundAt": "2024-10-23T02:38:01.015Z",
        "type": "MONEYLINE_3WAY",
        "market_name": "Everton @ Southampton",
        "participants": [
            "Southampton",
            "Everton"
        ],
        "outcome_payout": 2.95,
        "source": "BET_RIVERS",
        "participant": "Everton",
        "sport": "SOCCER",
        "implied_probability": 34.020955,
        "profit_potential": 195.0,
        "EV": 0.36181725,
        "event_start_time": "2024-11-02T15:00:00.000Z",
        "competition_instance_name": "2024-25 English Premier League"
    },
    {
        "key": "0ICj-ykxc-jD44",
        "edge": "PLUS_EV_AVERAGE",
        "lastFoundAt": "2024-10-23T02:38:01.015Z",
        "type": "MONEYLINE_3WAY",
        "market_name": "Newcastle United @ Chelsea",
        "participants": [
            "Chelsea",
            "Newcastle United"
        ],
        "outcome_payout": 4.2,
        "source": "BET_RIVERS",
        "participant": "Newcastle United",
        "sport": "SOCCER",
        "implied_probability": 23.849923,
        "profit_potential": 320.0,
        "EV": 0.1696766,
        "event_start_time": "2024-10-27T14:00:00.000Z",
        "competition_instance_name": "2024-25 English Premier League"
    },
    {
        "key": "j2Kw-ykxc-O2nS",
        "edge": "PLUS_EV_AVERAGE",
        "lastFoundAt": "2024-10-23T02:38:01.015Z",
        "type": "MONEYLINE_3WAY",
        "market_name": "Brentford @ Fulham",
        "participants": [
            "Brentford",
            "Fulham"
        ],
        "outcome_payout": 3.7,
        "source": "BET_RIVERS",
        "participant": "Brentford",
        "sport": "SOCCER",
        "implied_probability": 27.621224,
        "profit_potential": 270.0,
        "EV": 2.1985288,
        "event_start_time": "2024-11-04T20:00:00.000Z",
        "competition_instance_name": "2024-25 English Premier League"
    },
    {
        "key": "Bn2n-ykxc-DclS",
        "edge": "PLUS_EV_AVERAGE",
        "lastFoundAt": "2024-10-23T02:38:01.015Z",
        "type": "MONEYLINE_3WAY",
        "market_name": "Wolverhampton Wanderers @ Brighton & Hove Albion",
        "participants": [
            "Brighton & Hove Albion",
            "Wolverhampton Wanderers"
        ],
        "outcome_payout": 5.5,
        "source": "FAN_DUEL",
        "participant": "Wolverhampton Wanderers",
        "sport": "SOCCER",
        "implied_probability": 18.442429,
        "profit_potential": 450.0,
        "EV": 1.4333595,
        "event_start_time": "2024-10-26T14:00:00.000Z",
        "competition_instance_name": "2024-25 English Premier League"
    },
    {
        "key": "MIzf-ykxc-mH3k",
        "edge": "PLUS_EV_AVERAGE",
        "lastFoundAt": "2024-10-23T02:38:01.015Z",
        "type": "MONEYLINE_3WAY",
        "market_name": "Southampton @ Manchester City",
        "participants": [
            "Southampton",
            "Manchester City"
        ],
        "outcome_payout": 29.0,
        "source": "BET_PARX",
        "participant": "Southampton",
        "sport": "SOCCER",
        "implied_probability": 4.440169,
        "profit_potential": 2800.0,
        "EV": 28.764901,
        "event_start_time": "2024-10-26T14:00:00.000Z",
        "competition_instance_name": "2024-25 English Premier League"
    },
    {
        "key": "OlNe-ykxc-u4H0",
        "edge": "PLUS_EV_AVERAGE",
        "lastFoundAt": "2024-10-23T02:38:01.015Z",
        "type": "MONEYLINE_3WAY",
        "market_name": "Southampton @ Manchester City",
        "participants": [
            "Southampton",
            "Manchester City"
        ],
        "outcome_payout": 29.0,
        "source": "BET_RIVERS",
        "participant": "Southampton",
        "sport": "SOCCER",
        "implied_probability": 4.440169,
        "profit_potential": 2800.0,
        "EV": 28.764901,
        "event_start_time": "2024-10-26T14:00:00.000Z",
        "competition_instance_name": "2024-25 English Premier League"
    },
    {
        "key": "ONKl-ykxc-70Kw",
        "edge": "PLUS_EV_AVERAGE",
        "lastFoundAt": "2024-10-23T02:38:01.015Z",
        "type": "MONEYLINE_3WAY",
        "market_name": "Southampton @ Manchester City",
        "participants": [
            "Southampton",
            "Manchester City"
        ],
        "outcome_payout": 11.5,
        "source": "BET_PARX",
        "participant": null,
        "sport": null,
        "implied_probability": 8.873202,
        "profit_potential": 1050.0,
        "EV": 2.041823,
        "event_start_time": "2024-10-26T14:00:00.000Z",
        "competition_instance_name": "2024-25 English Premier League"
    },
    {
        "key": "b1gb-ykxc-9imY",
        "edge": "PLUS_EV_AVERAGE",
        "lastFoundAt": "2024-10-23T02:38:01.015Z",
        "type": "MONEYLINE_3WAY",
        "market_name": "Southampton @ Manchester City",
        "participants": [
            "Southampton",
            "Manchester City"
        ],
        "outcome_payout": 12.0,
        "source": "BET_RIVERS",
        "participant": null,
        "sport": null,
        "implied_probability": 8.873202,
        "profit_potential": 1100.0,
        "EV": 6.478424,
        "event_start_time": "2024-10-26T14:00:00.000Z",
        "competition_instance_name": "2024-25 English Premier League"
    },
    {
        "key": "Sin7-ykxc-G0v5",
        "edge": "PLUS_EV_AVERAGE",
        "lastFoundAt": "2024-10-23T02:38:01.015Z",
        "type": "MONEYLINE_3WAY",
        "market_name": "Bayer Leverkusen @ Werder Bremen",
        "participants": [
            "Bayer Leverkusen",
            "Werder Bremen"
        ],
        "outcome_payout": 6.0,
        "source": "BET_PARX",
        "participant": "Werder Bremen",
        "sport": "SOCCER",
        "implied_probability": 16.888225,
        "profit_potential": 500.0,
        "EV": 1.32935,
        "event_start_time": "2024-10-26T16:30:00.000Z",
        "competition_instance_name": "2024-25 German Bundesliga"
    },
    {
        "key": "Su5z-ykxc-PVhr",
        "edge": "PLUS_EV_AVERAGE",
        "lastFoundAt": "2024-10-23T02:38:01.015Z",
        "type": "MONEYLINE_3WAY",
        "market_name": "Bayer Leverkusen @ Werder Bremen",
        "participants": [
            "Bayer Leverkusen",
            "Werder Bremen"
        ],
        "outcome_payout": 6.1,
        "source": "BET_RIVERS",
        "participant": "Werder Bremen",
        "sport": "SOCCER",
        "implied_probability": 16.888225,
        "profit_potential": 510.0,
        "EV": 3.0181725,
        "event_start_time": "2024-10-26T16:30:00.000Z",
        "competition_instance_name": "2024-25 German Bundesliga"
    },
    {
        "key": "Bz30-ykxc-iEXw",
        "edge": "PLUS_EV_AVERAGE",
        "lastFoundAt": "2024-10-23T02:38:01.015Z",
        "type": "MONEYLINE_3WAY",
        "market_name": "Holstein Kiel @ VfB Stuttgart",
        "participants": [
            "VfB Stuttgart",
            "Holstein Kiel"
        ],
        "outcome_payout": 11.0,
        "source": "BET_PARX",
        "participant": "Holstein Kiel",
        "sport": "SOCCER",
        "implied_probability": 9.417836,
        "profit_potential": 1000.0,
        "EV": 3.596196,
        "event_start_time": "2024-10-26T13:30:00.000Z",
        "competition_instance_name": "2024-25 German Bundesliga"
    },
    {
        "key": "0KV2-ykxc-8uDV",
        "edge": "PLUS_EV_AVERAGE",
        "lastFoundAt": "2024-10-23T02:38:01.015Z",
        "type": "MONEYLINE_3WAY",
        "market_name": "Holstein Kiel @ VfB Stuttgart",
        "participants": [
            "VfB Stuttgart",
            "Holstein Kiel"
        ],
        "outcome_payout": 11.0,
        "source": "BET_RIVERS",
        "participant": "Holstein Kiel",
        "sport": "SOCCER",
        "implied_probability": 9.417836,
        "profit_potential": 1000.0,
        "EV": 3.596196,
        "event_start_time": "2024-10-26T13:30:00.000Z",
        "competition_instance_name": "2024-25 German Bundesliga"
    },
    {
        "key": "cAu4-ykxc-CcTd",
        "edge": "PLUS_EV_AVERAGE",
        "lastFoundAt": "2024-10-23T02:38:01.015Z",
        "type": "MONEYLINE_3WAY",
        "market_name": "Freiburg @ RB Leipzig",
        "participants": [
            "RB Leipzig",
            "Freiburg"
        ],
        "outcome_payout": 5.3,
        "source": "BET_RIVERS",
        "participant": "Freiburg",
        "sport": "SOCCER",
        "implied_probability": 19.209494,
        "profit_potential": 430.0,
        "EV": 1.8103182,
        "event_start_time": "2024-10-26T13:30:00.000Z",
        "competition_instance_name": "2024-25 German Bundesliga"
    },
    {
        "key": "w57s-ykxc-ym9a",
        "edge": "PLUS_EV_AVERAGE",
        "lastFoundAt": "2024-10-23T02:38:01.015Z",
        "type": "MONEYLINE_3WAY",
        "market_name": "Eintracht Frankfurt @ Union Berlin",
        "participants": [
            "Eintracht Frankfurt",
            "Union Berlin"
        ],
        "outcome_payout": 3.6,
        "source": "BET_RIVERS",
        "participant": null,
        "sport": null,
        "implied_probability": 27.944508,
        "profit_potential": 260.0,
        "EV": 0.6002288,
        "event_start_time": "2024-10-27T16:30:00.000Z",
        "competition_instance_name": "2024-25 German Bundesliga"
    },
    {
        "key": "81N5-ykxc-DMSk",
        "edge": "PLUS_EV_AVERAGE",
        "lastFoundAt": "2024-10-23T02:38:01.015Z",
        "type": "MONEYLINE_3WAY",
        "market_name": "Hoffenheim @ FC Heidenheim",
        "participants": [
            "Hoffenheim",
            "FC Heidenheim"
        ],
        "outcome_payout": 3.95,
        "source": "BET_RIVERS",
        "participant": null,
        "sport": null,
        "implied_probability": 25.503826,
        "profit_potential": 295.0,
        "EV": 0.7401127,
        "event_start_time": "2024-10-27T18:30:00.000Z",
        "competition_instance_name": "2024-25 German Bundesliga"
    },
    {
        "key": "n7fk-ykxc-6vFR",
        "edge": "PLUS_EV_AVERAGE",
        "lastFoundAt": "2024-10-23T02:38:01.015Z",
        "type": "MONEYLINE_3WAY",
        "market_name": "Hoffenheim @ FC Heidenheim",
        "participants": [
            "Hoffenheim",
            "FC Heidenheim"
        ],
        "outcome_payout": 3.2,
        "source": "BET_RIVERS",
        "participant": "Hoffenheim",
        "sport": "SOCCER",
        "implied_probability": 31.564113,
        "profit_potential": 220.0,
        "EV": 1.0051616,
        "event_start_time": "2024-10-27T18:30:00.000Z",
        "competition_instance_name": "2024-25 German Bundesliga"
    },
    {
        "key": "vixu-ykxc-6pqr",
        "edge": "PLUS_EV_AVERAGE",
        "lastFoundAt": "2024-10-23T02:38:01.015Z",
        "type": "MONEYLINE_3WAY",
        "market_name": "Borussia Moenchengladbach @ Mainz 05",
        "participants": [
            "Mainz 05",
            "Borussia Moenchengladbach"
        ],
        "outcome_payout": 4.0,
        "source": "BET_RIVERS",
        "participant": null,
        "sport": null,
        "implied_probability": 25.023808,
        "profit_potential": 300.0,
        "EV": 0.095232,
        "event_start_time": "2024-10-25T18:30:00.000Z",
        "competition_instance_name": "2024-25 German Bundesliga"
    },
    {
        "key": "sV1Y-ykxc-L2C4",
        "edge": "PLUS_EV_AVERAGE",
        "lastFoundAt": "2024-10-23T02:38:01.015Z",
        "type": "MONEYLINE_3WAY",
        "market_name": "Bayern Munich @ VfL Bochum",
        "participants": [
            "VfL Bochum",
            "Bayern Munich"
        ],
        "outcome_payout": 10.0,
        "source": "BET_RIVERS",
        "participant": null,
        "sport": null,
        "implied_probability": 10.174151,
        "profit_potential": 900.0,
        "EV": 1.74151,
        "event_start_time": "2024-10-27T14:30:00.000Z",
        "competition_instance_name": "2024-25 German Bundesliga"
    },
    {
        "key": "0lhA-ykxc-XsdJ",
        "edge": "PLUS_EV_AVERAGE",
        "lastFoundAt": "2024-10-23T02:38:01.015Z",
        "type": "MONEYLINE_3WAY",
        "market_name": "Bayern Munich @ VfL Bochum",
        "participants": [
            "VfL Bochum",
            "Bayern Munich"
        ],
        "outcome_payout": 15.0,
        "source": "BET_PARX",
        "participant": "VfL Bochum",
        "sport": "SOCCER",
        "implied_probability": 6.927411,
        "profit_potential": 1400.0,
        "EV": 3.911165,
        "event_start_time": "2024-10-27T14:30:00.000Z",
        "competition_instance_name": "2024-25 German Bundesliga"
    },
    {
        "key": "fUjm-ykxc-TRfD",
        "edge": "PLUS_EV_AVERAGE",
        "lastFoundAt": "2024-10-23T02:38:01.015Z",
        "type": "MONEYLINE_3WAY",
        "market_name": "Bayern Munich @ VfL Bochum",
        "participants": [
            "VfL Bochum",
            "Bayern Munich"
        ],
        "outcome_payout": 16.0,
        "source": "BET_RIVERS",
        "participant": "VfL Bochum",
        "sport": "SOCCER",
        "implied_probability": 6.927411,
        "profit_potential": 1500.0,
        "EV": 10.838576,
        "event_start_time": "2024-10-27T14:30:00.000Z",
        "competition_instance_name": "2024-25 German Bundesliga"
    },
    {
        "key": "Hy3q-ykxc-grmT",
        "edge": "PLUS_EV_AVERAGE",
        "lastFoundAt": "2024-10-23T02:38:01.015Z",
        "type": "MONEYLINE",
        "market_name": "Tennessee Titans @ Detroit Lions",
        "participants": [
            "Detroit Lions",
            "Tennessee Titans"
        ],
        "outcome_payout": 5.5,
        "source": "ESPN_BET",
        "participant": "Tennessee Titans",
        "sport": "AMERICAN_FOOTBALL",
        "implied_probability": 18.217197,
        "profit_potential": 450.0,
        "EV": 0.1945835,
        "event_start_time": "2024-10-27T17:00:00.000Z",
        "competition_instance_name": "2024-25 National Football League"
    },
    {
        "key": "xWoL-ykxc-sJ7R",
        "edge": "PLUS_EV_AVERAGE",
        "lastFoundAt": "2024-10-23T02:38:01.015Z",
        "type": "MONEYLINE",
        "market_name": "Baltimore Ravens @ Cleveland Browns",
        "participants": [
            "Baltimore Ravens",
            "Cleveland Browns"
        ],
        "outcome_payout": 4.8,
        "source": "BET_PARX",
        "participant": "Cleveland Browns",
        "sport": "AMERICAN_FOOTBALL",
        "implied_probability": 21.215783,
        "profit_potential": 380.0,
        "EV": 1.8357584,
        "event_start_time": "2024-10-27T17:00:00.000Z",
        "competition_instance_name": "2024-25 National Football League"
    },
    {
        "key": "jSTx-ykxc-3sRy",
        "edge": "PLUS_EV_AVERAGE",
        "lastFoundAt": "2024-10-23T02:38:01.015Z",
        "type": "MONEYLINE",
        "market_name": "Baltimore Ravens @ Cleveland Browns",
        "participants": [
            "Baltimore Ravens",
            "Cleveland Browns"
        ],
        "outcome_payout": 4.9,
        "source": "BET_RIVERS",
        "participant": "Cleveland Browns",
        "sport": "AMERICAN_FOOTBALL",
        "implied_probability": 21.215783,
        "profit_potential": 390.0,
        "EV": 3.9573367,
        "event_start_time": "2024-10-27T17:00:00.000Z",
        "competition_instance_name": "2024-25 National Football League"
    },
    {
        "key": "xdpf-ykxc-EriS",
        "edge": "PLUS_EV_AVERAGE",
        "lastFoundAt": "2024-10-23T02:38:01.015Z",
        "type": "MONEYLINE",
        "market_name": "Carolina Panthers @ Denver Broncos",
        "participants": [
            "Carolina Panthers",
            "Denver Broncos"
        ],
        "outcome_payout": 4.5,
        "source": "DRAFT_KINGS",
        "participant": "Carolina Panthers",
        "sport": "AMERICAN_FOOTBALL",
        "implied_probability": 22.348414,
        "profit_potential": 350.0,
        "EV": 0.567863,
        "event_start_time": "2024-10-27T20:25:00.000Z",
        "competition_instance_name": "2024-25 National Football League"
    },
    {
        "key": "bwaU-ykxc-HQQ6",
        "edge": "PLUS_EV_AVERAGE",
        "lastFoundAt": "2024-10-23T02:38:01.015Z",
        "type": "MONEYLINE",
        "market_name": "Kansas City Chiefs @ Las Vegas Raiders",
        "participants": [
            "Kansas City Chiefs",
            "Las Vegas Raiders"
        ],
        "outcome_payout": 5.0,
        "source": "ESPN_BET",
        "participant": "Las Vegas Raiders",
        "sport": "AMERICAN_FOOTBALL",
        "implied_probability": 20.278651,
        "profit_potential": 400.0,
        "EV": 1.393255,
        "event_start_time": "2024-10-27T20:25:00.000Z",
        "competition_instance_name": "2024-25 National Football League"
    },
    {
        "key": "agte-ykxc-ALlG",
        "edge": "PLUS_EV_AVERAGE",
        "lastFoundAt": "2024-10-23T02:38:01.015Z",
        "type": "MONEYLINE",
        "market_name": "New Orleans Saints @ Los Angeles Chargers",
        "participants": [
            "New Orleans Saints",
            "Los Angeles Chargers"
        ],
        "outcome_payout": 3.9,
        "source": "ESPN_BET",
        "participant": "New Orleans Saints",
        "sport": "AMERICAN_FOOTBALL",
        "implied_probability": 25.738743,
        "profit_potential": 290.0,
        "EV": 0.3810977,
        "event_start_time": "2024-10-27T20:05:00.000Z",
        "competition_instance_name": "2024-25 National Football League"
    },
    {
        "key": "5jSv-ykxc-i7El",
        "edge": "PLUS_EV_AVERAGE",
        "lastFoundAt": "2024-10-23T02:38:01.015Z",
        "type": "MONEYLINE_3WAY",
        "market_name": "Las Palmas @ Atletico Madrid",
        "participants": [
            "Atletico Madrid",
            "Las Palmas"
        ],
        "outcome_payout": 15.0,
        "source": "BET_RIVERS",
        "participant": "Las Palmas",
        "sport": "SOCCER",
        "implied_probability": 7.217642,
        "profit_potential": 1400.0,
        "EV": 8.26463,
        "event_start_time": "2024-11-03T13:00:00.000Z",
        "competition_instance_name": "2024-25 Spanish La Liga"
    },
    {
        "key": "G3EY-ykxc-OYZz",
        "edge": "PLUS_EV_AVERAGE",
        "lastFoundAt": "2024-10-23T02:38:01.015Z",
        "type": "MONEYLINE_3WAY",
        "market_name": "Hellas Verona @ Atalanta",
        "participants": [
            "Hellas Verona",
            "Atalanta"
        ],
        "outcome_payout": 8.0,
        "source": "BET_RIVERS",
        "participant": "Hellas Verona",
        "sport": "SOCCER",
        "implied_probability": 13.07499,
        "profit_potential": 700.0,
        "EV": 4.59992,
        "event_start_time": "2024-10-26T18:45:00.000Z",
        "competition_instance_name": "2024-25 Italian Serie A"
    },
    {
        "key": "GRM2-ykxc-WGVU",
        "edge": "PLUS_EV_AVERAGE",
        "lastFoundAt": "2024-10-23T02:38:01.015Z",
        "type": "MONEYLINE_3WAY",
        "market_name": "Real Betis @ Athletic Bilbao",
        "participants": [
            "Athletic Bilbao",
            "Real Betis"
        ],
        "outcome_payout": 5.1,
        "source": "BET_RIVERS",
        "participant": "Real Betis",
        "sport": "SOCCER",
        "implied_probability": 19.904182,
        "profit_potential": 410.0,
        "EV": 1.5113282,
        "event_start_time": "2024-11-03T20:00:00.000Z",
        "competition_instance_name": "2024-25 Spanish La Liga"
    },
    {
        "key": "I8St-ykxc-tmwy",
        "edge": "PLUS_EV_AVERAGE",
        "lastFoundAt": "2024-10-23T02:38:01.015Z",
        "type": "MONEYLINE_3WAY",
        "market_name": "Lecce @ Napoli",
        "participants": [
            "Lecce",
            "Napoli"
        ],
        "outcome_payout": 10.0,
        "source": "BET_PARX",
        "participant": "Lecce",
        "sport": "SOCCER",
        "implied_probability": 10.025358,
        "profit_potential": 900.0,
        "EV": 0.25358,
        "event_start_time": "2024-10-26T13:00:00.000Z",
        "competition_instance_name": "2024-25 Italian Serie A"
    },
    {
        "key": "ILCF-ykxc-Yg0e",
        "edge": "PLUS_EV_AVERAGE",
        "lastFoundAt": "2024-10-23T02:38:01.015Z",
        "type": "MONEYLINE_3WAY",
        "market_name": "Venezia @ Monza",
        "participants": [
            "Monza",
            "Venezia"
        ],
        "outcome_payout": 3.7,
        "source": "FAN_DUEL",
        "participant": "Venezia",
        "sport": "SOCCER",
        "implied_probability": 27.253831,
        "profit_potential": 270.0,
        "EV": 0.8391747,
        "event_start_time": "2024-10-27T14:00:00.000Z",
        "competition_instance_name": "2024-25 Italian Serie A"
    },
    {
        "key": "kM1w-ykxc-2fxx",
        "edge": "PLUS_EV_AVERAGE",
        "lastFoundAt": "2024-10-23T02:38:01.015Z",
        "type": "MONEYLINE_3WAY",
        "market_name": "Houston Dynamo FC @ Seattle Sounders FC",
        "participants": [
            "Houston Dynamo FC",
            "Seattle Sounders FC"
        ],
        "outcome_payout": 4.6,
        "source": "DRAFT_KINGS",
        "participant": "Houston Dynamo FC",
        "sport": "SOCCER",
        "implied_probability": 22.003735,
        "profit_potential": 360.0,
        "EV": 1.217181,
        "event_start_time": "2024-10-29T01:00:00.000Z",
        "competition_instance_name": "2024 Major League Soccer"
    },
    {
        "key": "M55D-ykxc-AHEM",
        "edge": "PLUS_EV_AVERAGE",
        "lastFoundAt": "2024-10-23T02:38:01.015Z",
        "type": "MONEYLINE_3WAY",
        "market_name": "Getafe @ Celta Vigo",
        "participants": [
            "Celta Vigo",
            "Getafe"
        ],
        "outcome_payout": 4.5,
        "source": "BET_RIVERS",
        "participant": "Getafe",
        "sport": "SOCCER",
        "implied_probability": 22.226584,
        "profit_potential": 350.0,
        "EV": 0.019628,
        "event_start_time": "2024-11-04T20:00:00.000Z",
        "competition_instance_name": "2024-25 Spanish La Liga"
    },
    {
        "key": "Mgn9-ykxc-Ijo1",
        "edge": "PLUS_EV_AVERAGE",
        "lastFoundAt": "2024-10-23T02:38:01.015Z",
        "type": "MONEYLINE_3WAY",
        "market_name": "Real Madrid @ Valencia",
        "participants": [
            "Real Madrid",
            "Valencia"
        ],
        "outcome_payout": 6.25,
        "source": "BET_RIVERS",
        "participant": "Valencia",
        "sport": "SOCCER",
        "implied_probability": 16.057683,
        "profit_potential": 525.0,
        "EV": 0.36051875,
        "event_start_time": "2024-11-02T20:00:00.000Z",
        "competition_instance_name": "2024-25 Spanish La Liga"
    },
    {
        "key": "O92A-ykxc-1Iu5",
        "edge": "PLUS_EV_AVERAGE",
        "lastFoundAt": "2024-10-23T02:38:01.015Z",
        "type": "MONEYLINE",
        "market_name": "ASVEL @ Barcelona",
        "participants": [
            "Barcelona",
            "ASVEL"
        ],
        "outcome_payout": 6.4,
        "source": "FAN_DUEL",
        "participant": "ASVEL",
        "sport": "BASKETBALL",
        "implied_probability": 16.547255,
        "profit_potential": 540.0,
        "EV": 5.902432,
        "event_start_time": "2024-10-25T18:30:00.000Z",
        "competition_instance_name": "2024-25 EuroLeague"
    },
    {
        "key": "pIFe-ykxc-Ht5L",
        "edge": "PLUS_EV_AVERAGE",
        "lastFoundAt": "2024-10-23T02:38:01.015Z",
        "type": "MONEYLINE_3WAY",
        "market_name": "Lecce @ Napoli",
        "participants": [
            "Lecce",
            "Napoli"
        ],
        "outcome_payout": 10.0,
        "source": "BET_RIVERS",
        "participant": "Lecce",
        "sport": "SOCCER",
        "implied_probability": 10.025358,
        "profit_potential": 900.0,
        "EV": 0.25358,
        "event_start_time": "2024-10-26T13:00:00.000Z",
        "competition_instance_name": "2024-25 Italian Serie A"
    },
    {
        "key": "pu7i-ykxc-HC8U",
        "edge": "PLUS_EV_AVERAGE",
        "lastFoundAt": "2024-10-23T02:38:01.015Z",
        "type": "MONEYLINE_3WAY",
        "market_name": "Las Palmas @ Atletico Madrid",
        "participants": [
            "Atletico Madrid",
            "Las Palmas"
        ],
        "outcome_payout": 15.0,
        "source": "BET_PARX",
        "participant": "Las Palmas",
        "sport": "SOCCER",
        "implied_probability": 7.217642,
        "profit_potential": 1400.0,
        "EV": 8.26463,
        "event_start_time": "2024-11-03T13:00:00.000Z",
        "competition_instance_name": "2024-25 Spanish La Liga"
    },
    {
        "key": "Q0WK-ykxc-cfn0",
        "edge": "PLUS_EV_AVERAGE",
        "lastFoundAt": "2024-10-23T02:38:01.015Z",
        "type": "MONEYLINE_3WAY",
        "market_name": "Colorado Rapids @ LA Galaxy",
        "participants": [
            "Colorado Rapids",
            "LA Galaxy"
        ],
        "outcome_payout": 5.8,
        "source": "BET_RIVERS",
        "participant": "Colorado Rapids",
        "sport": "SOCCER",
        "implied_probability": 17.93822,
        "profit_potential": 480.0,
        "EV": 4.041676,
        "event_start_time": "2024-10-27T03:00:00.000Z",
        "competition_instance_name": "2024 Major League Soccer"
    },
    {
        "key": "qSYh-ykxc-ciyP",
        "edge": "PLUS_EV_AVERAGE",
        "lastFoundAt": "2024-10-23T02:38:01.015Z",
        "type": "MONEYLINE_3WAY",
        "market_name": "Las Palmas @ Atletico Madrid",
        "participants": [
            "Atletico Madrid",
            "Las Palmas"
        ],
        "outcome_payout": 14.0,
        "source": "FAN_DUEL",
        "participant": "Las Palmas",
        "sport": "SOCCER",
        "implied_probability": 7.217642,
        "profit_potential": 1300.0,
        "EV": 1.046988,
        "event_start_time": "2024-11-03T13:00:00.000Z",
        "competition_instance_name": "2024-25 Spanish La Liga"
    },
    {
        "key": "UJ57-ykxc-TEsp",
        "edge": "PLUS_EV_AVERAGE",
        "lastFoundAt": "2024-10-23T02:38:01.015Z",
        "type": "MONEYLINE_3WAY",
        "market_name": "Colorado Rapids @ LA Galaxy",
        "participants": [
            "Colorado Rapids",
            "LA Galaxy"
        ],
        "outcome_payout": 5.8,
        "source": "BET_PARX",
        "participant": "Colorado Rapids",
        "sport": "SOCCER",
        "implied_probability": 17.93822,
        "profit_potential": 480.0,
        "EV": 4.041676,
        "event_start_time": "2024-10-27T03:00:00.000Z",
        "competition_instance_name": "2024 Major League Soccer"
    },
    {
        "key": "VdOb-ykxc-u8TM",
        "edge": "PLUS_EV_AVERAGE",
        "lastFoundAt": "2024-10-23T02:38:01.015Z",
        "type": "MONEYLINE_3WAY",
        "market_name": "Colorado Rapids @ LA Galaxy",
        "participants": [
            "Colorado Rapids",
            "LA Galaxy"
        ],
        "outcome_payout": 5.7,
        "source": "FAN_DUEL",
        "participant": "Colorado Rapids",
        "sport": "SOCCER",
        "implied_probability": 17.93822,
        "profit_potential": 470.0,
        "EV": 2.247854,
        "event_start_time": "2024-10-27T03:00:00.000Z",
        "competition_instance_name": "2024 Major League Soccer"
    }
]